ccai_python/__init__.py
ccai_python/ccai.py
ccai_python/examples/async_example.py
ccai_python/examples/basic_example.py
ccai_python/sms/__init__.py
ccai_python/sms/sms.py
ccai_python-1.0.0.dist-info/METADATA
ccai_python-1.0.0.dist-info/WHEEL
ccai_python-1.0.0.dist-info/top_level.txt
ccai_python-1.0.0.dist-info/RECORD
