Metadata-Version: 2.4
Name: ccai-python
Version: 1.0.0
Summary: Python client for CloudContactAI API
Author: CloudContactAI LLC
License: MIT
Project-URL: Homepage, https://github.com/cloudcontactai/ccai-python
Project-URL: Bug Tracker, https://github.com/cloudcontactai/ccai-python/issues
Keywords: sms,api,client,cloud,contact,ai,cloudcontactai
Classifier: Programming Language :: Python :: 3
Classifier: Programming Language :: Python :: 3.10
Classifier: Programming Language :: Python :: 3.11
Classifier: Programming Language :: Python :: 3.12
Classifier: License :: OSI Approved :: MIT License
Classifier: Operating System :: OS Independent
Requires-Python: >=3.10
Requires-Dist: requests>=2.31.0
Requires-Dist: pydantic>=2.5.0
